{"updated": "2026-05-21", "cat": 527349, "slug": "alimentacao", "total": 46, "min": 2.3493, "max": 16.1007, "products": [{"id": 5532653, "title": "Hobby Protogen 20ml", "price": 8.5977, "pf": "8,60 €", "pp": null, "ppf": null, "url": "https://www.aquariumlife.pt/product/hobby-protogen-20ml", "cart": "https://www.aquariumlife.pt/cart/add/hobby-protogen-20ml", "img": "https://cdn-shopkit.com/assets/store/img/no-img.png"}, {"id": 5532595, "title": "Dennerle Betta Booster 12g", "price": 6.9864, "pf": "6,99 €", "pp": null, "ppf": null, "url": "https://www.aquariumlife.pt/product/dennerle-betta-booster-12g", "cart": "https://www.aquariumlife.pt/cart/add/dennerle-betta-booster-12g", "img": "https://cdn-shopkit.com/assets/store/img/no-img.png"}, {"id": 5532594, "title": "Dennerle Cookies Special Menu 100ml", "price": 6.9864, "pf": "6,99 €", "pp": null, "ppf": null, "url": "https://www.aquariumlife.pt/product/dennerle-cookies-special-menu-100ml", "cart": "https://www.aquariumlife.pt/cart/add/dennerle-cookies-special-menu-100ml", "img": "https://cdn-shopkit.com/assets/store/img/no-img.png"}, {"id": 5532593, "title": "Dennerle Color Booster 100ml", "price": 6.9864, "pf": "6,99 €", "pp": null, "ppf": null, "url": "https://www.aquariumlife.pt/product/dennerle-color-booster-100ml", "cart": "https://www.aquariumlife.pt/cart/add/dennerle-color-booster-100ml", "img": "https://cdn-shopkit.com/assets/store/img/no-img.png"}, {"id": 5532592, "title": "Dennerle Complete Gourmet Menu 100ml", "price": 6.9864, "pf": "6,99 €", "pp": null, "ppf": null, "url": "https://www.aquariumlife.pt/product/dennerle-complete-gourmet-menu-100ml", "cart": "https://www.aquariumlife.pt/cart/add/dennerle-complete-gourmet-menu-100ml", "img": "https://cdn-shopkit.com/assets/store/img/no-img.png"}, {"id": 5532591, "title": "Shrimp King Dadap Leaves 10x", "price": 9.987599999999999, "pf": "9,99 €", "pp": null, "ppf": null, "url": "https://www.aquariumlife.pt/product/shrimp-king-dadap-leaves-10x", "cart": "https://www.aquariumlife.pt/cart/add/shrimp-king-dadap-leaves-10x", "img": "https://cdn-shopkit.com/assets/store/img/no-img.png"}, {"id": 5532590, "title": "Shrimp King Snail Stixx 40g", "price": 11.9925, "pf": "11,99 €", "pp": null, "ppf": null, "url": "https://www.aquariumlife.pt/product/shrimp-king-snail-stixx-40g-", "cart": "https://www.aquariumlife.pt/cart/add/shrimp-king-snail-stixx-40g-", "img": "https://cdn-shopkit.com/assets/store/img/no-img.png"}, {"id": 5513012, "title": "Gamma Brineshrimp Garlic flat pack 250g", "price": 8.1549, "pf": "8,15 €", "pp": null, "ppf": null, "url": "https://www.aquariumlife.pt/product/gamma-brineshrimp-garlic-flat-pack-250g", "cart": "https://www.aquariumlife.pt/cart/add/gamma-brineshrimp-garlic-flat-pack-250g", "img": "https://cdn-shopkit.com/assets/store/img/no-img.png"}, {"id": 5513011, "title": "Gamma Mysis shrimp flat pack 250g", "price": 7.502999999999999, "pf": "7,50 €", "pp": null, "ppf": null, "url": "https://www.aquariumlife.pt/product/gamma-mysis-shrimp-flat-pack-250g", "cart": "https://www.aquariumlife.pt/cart/add/gamma-mysis-shrimp-flat-pack-250g", "img": "https://cdn-shopkit.com/assets/store/img/no-img.png"}, {"id": 5513010, "title": "Gamma Copepod garlic blister 100g", "price": 4.4034, "pf": "4,40 €", "pp": null, "ppf": null, "url": "https://www.aquariumlife.pt/product/gamma-copepod-garlic-blister-100g", "cart": "https://www.aquariumlife.pt/cart/add/gamma-copepod-garlic-blister-100g", "img": "https://cdn-shopkit.com/assets/store/img/no-img.png"}, {"id": 5513009, "title": "Gamma Marine Quintet blister 100g", "price": 5.0061, "pf": "5,01 €", "pp": null, "ppf": null, "url": "https://www.aquariumlife.pt/product/gamma-marine-quintet-blister-100g", "cart": "https://www.aquariumlife.pt/cart/add/gamma-marine-quintet-blister-100g", "img": "https://cdn-shopkit.com/assets/store/img/no-img.png"}, {"id": 5513008, "title": "Gamma Cichlid Diet blister 100g", "price": 4.4034, "pf": "4,40 €", "pp": null, "ppf": null, "url": "https://www.aquariumlife.pt/product/gamma-cichlid-diet-blister-100g", "cart": "https://www.aquariumlife.pt/cart/add/gamma-cichlid-diet-blister-100g", "img": "https://cdn-shopkit.com/assets/store/img/no-img.png"}, {"id": 5513007, "title": "Gamma White Mosquito larvae blister 100g", "price": 5.0061, "pf": "5,01 €", "pp": null, "ppf": null, "url": "https://www.aquariumlife.pt/product/gamma-white-mosquito-larvae-blister-100g", "cart": "https://www.aquariumlife.pt/cart/add/gamma-white-mosquito-larvae-blister-100g", "img": "https://cdn-shopkit.com/assets/store/img/no-img.png"}, {"id": 5513006, "title": "Gamma Daphnia blister 100g", "price": 3.198, "pf": "3,20 €", "pp": null, "ppf": null, "url": "https://www.aquariumlife.pt/product/gamma-daphnia-blister-100g", "cart": "https://www.aquariumlife.pt/cart/add/gamma-daphnia-blister-100g", "img": "https://cdn-shopkit.com/assets/store/img/no-img.png"}, {"id": 5513005, "title": "Gamma Mysis shrimp garlic blister 100g", "price": 3.7514999999999996, "pf": "3,75 €", "pp": null, "ppf": null, "url": "https://www.aquariumlife.pt/product/gamma-mysis-shrimp-garlic-blister-100g", "cart": "https://www.aquariumlife.pt/cart/add/gamma-mysis-shrimp-garlic-blister-100g", "img": "https://cdn-shopkit.com/assets/store/img/no-img.png"}, {"id": 5513004, "title": "Gamma Cyclops blister 100g", "price": 3.7514999999999996, "pf": "3,75 €", "pp": null, "ppf": null, "url": "https://www.aquariumlife.pt/product/gamma-cyclops-blister-100g-", "cart": "https://www.aquariumlife.pt/cart/add/gamma-cyclops-blister-100g-", "img": "https://cdn-shopkit.com/assets/store/img/no-img.png"}, {"id": 5513003, "title": "Gamma Brineshrimp garlic blister 100g", "price": 3.7514999999999996, "pf": "3,75 €", "pp": null, "ppf": null, "url": "https://www.aquariumlife.pt/product/gamma-brineshrimp-garlic-blister-100g", "cart": "https://www.aquariumlife.pt/cart/add/gamma-brineshrimp-garlic-blister-100g", "img": "https://cdn-shopkit.com/assets/store/img/no-img.png"}, {"id": 5513002, "title": "Gamma Discus Diet blister 100g", "price": 3.7514999999999996, "pf": "3,75 €", "pp": null, "ppf": null, "url": "https://www.aquariumlife.pt/product/gamma-discus-diet-blister-100g", "cart": "https://www.aquariumlife.pt/cart/add/gamma-discus-diet-blister-100g", "img": "https://cdn-shopkit.com/assets/store/img/no-img.png"}, {"id": 5513001, "title": "Gamma Tubifex blister 100g", "price": 3.7514999999999996, "pf": "3,75 €", "pp": null, "ppf": null, "url": "https://www.aquariumlife.pt/product/gamma-tubifex-blister-100g", "cart": "https://www.aquariumlife.pt/cart/add/gamma-tubifex-blister-100g", "img": "https://cdn-shopkit.com/assets/store/img/no-img.png"}, {"id": 5513000, "title": "Gamma Bloodworm blister 100g", "price": 3.7514999999999996, "pf": "3,75 €", "pp": null, "ppf": null, "url": "https://www.aquariumlife.pt/product/gamma-bloodworm-blister-100g", "cart": "https://www.aquariumlife.pt/cart/add/gamma-bloodworm-blister-100g", "img": "https://cdn-shopkit.com/assets/store/img/no-img.png"}, {"id": 5512999, "title": "Gamma Brineshrimp blister 100g", "price": 3.7514999999999996, "pf": "3,75 €", "pp": null, "ppf": null, "url": "https://www.aquariumlife.pt/product/gamma-brineshrimp-blister-100g-", "cart": "https://www.aquariumlife.pt/cart/add/gamma-brineshrimp-blister-100g-", "img": "https://cdn-shopkit.com/assets/store/img/no-img.png"}, {"id": 5512998, "title": "Gamma mini bloodworm blister 100g", "price": 3.7514999999999996, "pf": "3,75 €", "pp": null, "ppf": null, "url": "https://www.aquariumlife.pt/product/gamma-mini-bloodworm-blister-100g", "cart": "https://www.aquariumlife.pt/cart/add/gamma-mini-bloodworm-blister-100g", "img": "https://cdn-shopkit.com/assets/store/img/no-img.png"}, {"id": 5445191, "title": "Hikari Sinking wafers 50g", "price": 4.6494, "pf": "4,65 €", "pp": null, "ppf": null, "url": "https://www.aquariumlife.pt/product/hikari-sinking-wafers-50g", "cart": "https://www.aquariumlife.pt/cart/add/hikari-sinking-wafers-50g", "img": "https://cdn-shopkit.com/assets/store/img/no-img.png"}, {"id": 5445190, "title": "Hikari Micro Pellets 45g", "price": 6.9495000000000005, "pf": "6,95 €", "pp": null, "ppf": null, "url": "https://www.aquariumlife.pt/product/hikari-micro-pellets-45g", "cart": "https://www.aquariumlife.pt/cart/add/hikari-micro-pellets-45g", "img": "https://cdn-shopkit.com/assets/store/img/no-img.png"}, {"id": 5445188, "title": "Hikari micro wafers 45g", "price": 4.944599999999999, "pf": "4,94 €", "pp": null, "ppf": null, "url": "https://www.aquariumlife.pt/product/hikari-micro-wafers-45g", "cart": "https://www.aquariumlife.pt/cart/add/hikari-micro-wafers-45g", "img": "https://cdn-shopkit.com/assets/store/img/no-img.png"}, {"id": 5445112, "title": "Tropical Goldfish Flake Color (100 ml)", "price": 2.3493, "pf": "2,35 €", "pp": null, "ppf": null, "url": "https://www.aquariumlife.pt/product/tropical-goldfish-flake-color-100-ml", "cart": "https://www.aquariumlife.pt/cart/add/tropical-goldfish-flake-color-100-ml", "img": "https://cdn-shopkit.com/assets/store/img/no-img.png"}, {"id": 5445111, "title": "Tropical Betta Flakes (100 ml)", "price": 4.6494, "pf": "4,65 €", "pp": null, "ppf": null, "url": "https://www.aquariumlife.pt/product/tropical-betta-flakes-100-ml", "cart": "https://www.aquariumlife.pt/cart/add/tropical-betta-flakes-100-ml", "img": "https://cdn-shopkit.com/assets/store/img/no-img.png"}, {"id": 5445110, "title": "Tropical Crusta Sticks (100 ml)", "price": 5.805599999999999, "pf": "5,81 €", "pp": null, "ppf": null, "url": "https://www.aquariumlife.pt/product/tropical-crusta-sticks-100-ml", "cart": "https://www.aquariumlife.pt/cart/add/tropical-crusta-sticks-100-ml", "img": "https://cdn-shopkit.com/assets/store/img/no-img.png"}, {"id": 5445108, "title": "Tropical Shrimp Sticks (100 ml)", "price": 4.5018, "pf": "4,50 €", "pp": null, "ppf": null, "url": "https://www.aquariumlife.pt/product/tropical-shrimp-sticks-100-ml", "cart": "https://www.aquariumlife.pt/cart/add/tropical-shrimp-sticks-100-ml", "img": "https://cdn-shopkit.com/assets/store/img/no-img.png"}, {"id": 5445107, "title": "Tropical Welsi Gran (250 ml)", "price": 7.097099999999999, "pf": "7,10 €", "pp": null, "ppf": null, "url": "https://www.aquariumlife.pt/product/tropical-welsi-gran-250-ml", "cart": "https://www.aquariumlife.pt/cart/add/tropical-welsi-gran-250-ml", "img": "https://cdn-shopkit.com/assets/store/img/no-img.png"}, {"id": 5445106, "title": "Tropical Spirulina Flakes (250 ml)", "price": 6.0516, "pf": "6,05 €", "pp": null, "ppf": null, "url": "https://www.aquariumlife.pt/product/tropical-spirulina-flakes-250-ml", "cart": "https://www.aquariumlife.pt/cart/add/tropical-spirulina-flakes-250-ml", "img": "https://cdn-shopkit.com/assets/store/img/no-img.png"}, {"id": 5445105, "title": "Tropical Spirulina 36% Granulat (250 ml)", "price": 16.1007, "pf": "16,10 €", "pp": null, "ppf": null, "url": "https://www.aquariumlife.pt/product/tropical-spirulina-36-granulat-250-ml", "cart": "https://www.aquariumlife.pt/cart/add/tropical-spirulina-36-granulat-250-ml", "img": "https://cdn-shopkit.com/assets/store/img/no-img.png"}, {"id": 5445104, "title": "Tropical Cichlid Herbivore S (250 ml)", "price": 6.1992, "pf": "6,20 €", "pp": null, "ppf": null, "url": "https://www.aquariumlife.pt/product/tropical-cichlid-herbivore-s-250-ml", "cart": "https://www.aquariumlife.pt/cart/add/tropical-cichlid-herbivore-s-250-ml", "img": "https://cdn-shopkit.com/assets/store/img/no-img.png"}, {"id": 5445103, "title": "Tropical D-Allio Plus Granulat (250 ml)", "price": 10.602599999999999, "pf": "10,60 €", "pp": null, "ppf": null, "url": "https://www.aquariumlife.pt/product/tropical-d-allio-plus-granulat-250-ml", "cart": "https://www.aquariumlife.pt/cart/add/tropical-d-allio-plus-granulat-250-ml", "img": "https://cdn-shopkit.com/assets/store/img/no-img.png"}, {"id": 5445102, "title": "Tropical Cichlid Gran (250 ml)", "price": 8.4993, "pf": "8,50 €", "pp": null, "ppf": null, "url": "https://www.aquariumlife.pt/product/tropical-cichlid-gran-250-ml", "cart": "https://www.aquariumlife.pt/cart/add/tropical-cichlid-gran-250-ml", "img": "https://cdn-shopkit.com/assets/store/img/no-img.png"}, {"id": 5445092, "title": "Tropical Vitality & Color Granulat 250ml", "price": 8.7453, "pf": "8,75 €", "pp": null, "ppf": null, "url": "https://www.aquariumlife.pt/product/tropical-vitality-color-granulat-250ml", "cart": "https://www.aquariumlife.pt/cart/add/tropical-vitality-color-granulat-250ml", "img": "https://cdn-shopkit.com/assets/store/img/no-img.png"}, {"id": 5445091, "title": "Tropical Vitality & Color Granulat 100ml", "price": 4.4526, "pf": "4,45 €", "pp": null, "ppf": null, "url": "https://www.aquariumlife.pt/product/tropical-vitality-color-granulat-100ml", "cart": "https://www.aquariumlife.pt/cart/add/tropical-vitality-color-granulat-100ml", "img": "https://cdn-shopkit.com/assets/store/img/no-img.png"}, {"id": 5445090, "title": "Tropical Malawi Chips (250 ml)", "price": 8.9544, "pf": "8,95 €", "pp": null, "ppf": null, "url": "https://www.aquariumlife.pt/product/tropical-malawi-chips-250-ml", "cart": "https://www.aquariumlife.pt/cart/add/tropical-malawi-chips-250-ml", "img": "https://cdn-shopkit.com/assets/store/img/no-img.png"}, {"id": 5445089, "title": "Tropical Discus Granulat D-50 Plus Baby (100 ml)", "price": 5.805599999999999, "pf": "5,81 €", "pp": null, "ppf": null, "url": "https://www.aquariumlife.pt/product/tropical-discus-granulat-d-50-plus-baby-100-ml", "cart": "https://www.aquariumlife.pt/cart/add/tropical-discus-granulat-d-50-plus-baby-100-ml", "img": "https://cdn-shopkit.com/assets/store/img/no-img.png"}, {"id": 5445088, "title": "Tropical Discus Granulat D-50 Plus (250 ml)", "price": 8.5485, "pf": "8,55 €", "pp": null, "ppf": null, "url": "https://www.aquariumlife.pt/product/tropical-discus-granulat-d-50-plus-250-ml", "cart": "https://www.aquariumlife.pt/cart/add/tropical-discus-granulat-d-50-plus-250-ml", "img": "https://cdn-shopkit.com/assets/store/img/no-img.png"}, {"id": 5445087, "title": "Tropical Discus Granulat D-50 Plus (100 ml)", "price": 4.305, "pf": "4,31 €", "pp": null, "ppf": null, "url": "https://www.aquariumlife.pt/product/tropical-discus-granulat-d-50-plus-100-ml", "cart": "https://www.aquariumlife.pt/cart/add/tropical-discus-granulat-d-50-plus-100-ml", "img": "https://cdn-shopkit.com/assets/store/img/no-img.png"}, {"id": 5445086, "title": "Tropical D-50 Plus Flakes (250 ml)", "price": 6.4452, "pf": "6,45 €", "pp": null, "ppf": null, "url": "https://www.aquariumlife.pt/product/tropical-d-50-plus-flakes-250-ml", "cart": "https://www.aquariumlife.pt/cart/add/tropical-d-50-plus-flakes-250-ml", "img": "https://cdn-shopkit.com/assets/store/img/no-img.png"}, {"id": 5445085, "title": "Tropical Supervit Granulat (250 ml)", "price": 7.7982, "pf": "7,80 €", "pp": null, "ppf": null, "url": "https://www.aquariumlife.pt/product/tropical-supervit-granulat-250-ml", "cart": "https://www.aquariumlife.pt/cart/add/tropical-supervit-granulat-250-ml", "img": "https://cdn-shopkit.com/assets/store/img/no-img.png"}, {"id": 5445084, "title": "Tropical Supervit Granulat (100 ml)", "price": 3.8991, "pf": "3,90 €", "pp": null, "ppf": null, "url": "https://www.aquariumlife.pt/product/tropical-supervit-granulat-100-ml", "cart": "https://www.aquariumlife.pt/cart/add/tropical-supervit-granulat-100-ml", "img": "https://cdn-shopkit.com/assets/store/img/no-img.png"}, {"id": 5445081, "title": "Tropical Supervit Tablets B (250 ml)", "price": 11.746500000000001, "pf": "11,75 €", "pp": null, "ppf": null, "url": "https://www.aquariumlife.pt/product/tropical-supervit-tablets-b-250-ml", "cart": "https://www.aquariumlife.pt/cart/add/tropical-supervit-tablets-b-250-ml", "img": "https://cdn-shopkit.com/assets/store/img/no-img.png"}, {"id": 5445080, "title": "Tropical Supervit Tablets B (50 ml)", "price": 4.944599999999999, "pf": "4,94 €", "pp": null, "ppf": null, "url": "https://www.aquariumlife.pt/product/tropical-supervit-tablets-b-50-ml", "cart": "https://www.aquariumlife.pt/cart/add/tropical-supervit-tablets-b-50-ml", "img": "https://cdn-shopkit.com/assets/store/img/no-img.png"}]}